{
  "project_info": {
    "project_number": "591528445932",
    "project_id": "saved-47621",
    "storage_bucket": "saved-47621.appspot.com"
  },
  "client": [
    {
      "client_info": {
        "mobilesdk_app_id": "1:591528445932:android:7cbcdb860e86ecd22062c9",
        "android_client_info": {
          "package_name": "com.example.finalregistration"
        }
      },
      "oauth_client": [
        {
          "client_id": "591528445932-pu7r5ksfsctvl7i2rab9ie73hiackmeo.apps.googleusercontent.com",
          "client_type": 3
        }
      ],
      "api_key": [
        {
          "current_key": "AIzaSyBQide9_MTjn6Zl5sSwwupFblXQcpUhcy0"
        }
      ],
      "services": {
        "appinvite_service": {
          "other_platform_oauth_client": [
            {
              "client_id": "591528445932-pu7r5ksfsctvl7i2rab9ie73hiackmeo.apps.googleusercontent.com",
              "client_type": 3
            }
          ]
        }
      }
    }
  ],
  "configuration_version": "1"
}